pymentoring/App.py
pymentoring/__init__.py
pymentoring/anagrams/__init__.py
pymentoring/anagrams/anagrams.py
pymentoring/anagrams/anagrams_app.py
pymentoring/monaco/__init__.py
pymentoring/monaco/data/abbreviations.txt
pymentoring/monaco/monaco2018.py
pymentoring/monaco/monaco2018_app.py
pymentoring/mycollections/__init__.py
pymentoring/mycollections/constants.py
pymentoring/mycollections/my_collections.py
pymentoring/mycollections/my_collections_app.py
pymentoring/utils/__init__.py
pymentoring/utils/string_utils.py
pymentoring-0.1.0.dist-info/METADATA
pymentoring-0.1.0.dist-info/WHEEL
pymentoring-0.1.0.dist-info/entry_points.txt
pymentoring-0.1.0.dist-info/RECORD
